odoo/addons/stock_location_lockdown/README.rst
odoo/addons/stock_location_lockdown/__init__.py
odoo/addons/stock_location_lockdown/__manifest__.py
odoo/addons/stock_location_lockdown/i18n/fr.po
odoo/addons/stock_location_lockdown/i18n/it.po
odoo/addons/stock_location_lockdown/i18n/pt.po
odoo/addons/stock_location_lockdown/i18n/stock_location_lockdown.pot
odoo/addons/stock_location_lockdown/i18n/zh_CN.po
odoo/addons/stock_location_lockdown/models/__init__.py
odoo/addons/stock_location_lockdown/models/stock_location.py
odoo/addons/stock_location_lockdown/models/stock_quant.py
odoo/addons/stock_location_lockdown/readme/CONTRIBUTORS.rst
odoo/addons/stock_location_lockdown/readme/DESCRIPTION.rst
odoo/addons/stock_location_lockdown/readme/USAGE.rst
odoo/addons/stock_location_lockdown/static/description/icon.png
odoo/addons/stock_location_lockdown/static/description/index.html
odoo/addons/stock_location_lockdown/tests/__init__.py
odoo/addons/stock_location_lockdown/tests/test_block_stock_location_entrance.py
odoo/addons/stock_location_lockdown/views/stock_location.xml
odoo14_addon_stock_location_lockdown-14.0.1.0.1.dev7.dist-info/METADATA
odoo14_addon_stock_location_lockdown-14.0.1.0.1.dev7.dist-info/WHEEL
odoo14_addon_stock_location_lockdown-14.0.1.0.1.dev7.dist-info/top_level.txt
odoo14_addon_stock_location_lockdown-14.0.1.0.1.dev7.dist-info/RECORD
